{
  "picks": [
    {
      "id": "SPD_LVA_NYL_20251217",
      "type": "Spread",
      "matchup": "New York Liberty @ Las Vegas Aces",
      "selection": "Las Vegas Aces -2.5",
      "line": "-2.5",
      "odds_str": "-110",
      "odds_dec": 1.91,
      "prob": 0.55,
      "edge": 0.16724999999999995,
      "wager": "1.0% Unit",
      "score": 3.344999999999999,
      "status": "Pending",
      "result": null,
      "profit": 0,
      "created_at": "2025-12-17T14:40:05.604815",
      "pick_id": "SPD_LVA_NYL_20251217",
      "placed_at": "2025-12-17T14:40:05.604815",
      "profit_loss": 0.0,
      "stake": null
    },
    {
      "id": "TOT_LVA_NYL_20251217",
      "type": "Total Points",
      "matchup": "New York Liberty @ Las Vegas Aces",
      "selection": "Over 172.5",
      "line": "172.5",
      "odds_str": "-110",
      "odds_dec": 1.91,
      "prob": 0.56,
      "edge": 0.27348749999999994,
      "wager": "1.0% Unit",
      "score": 27.348749999999995,
      "status": "Pending",
      "result": null,
      "profit": 0,
      "created_at": "2025-12-17T14:40:05.604819",
      "pick_id": "TOT_LVA_NYL_20251217",
      "placed_at": "2025-12-17T14:40:05.604819",
      "profit_loss": 0.0,
      "stake": null
    },
    {
      "id": "TOT_CON_SEA_20251217",
      "type": "Total Points",
      "matchup": "Seattle Storm @ Connecticut Sun",
      "selection": "Over 158.5",
      "line": "158.5",
      "odds_str": "-110",
      "odds_dec": 1.91,
      "prob": 0.56,
      "edge": 0.3445999999999998,
      "wager": "1.0% Unit",
      "score": 34.45999999999998,
      "status": "Pending",
      "result": null,
      "profit": 0,
      "created_at": "2025-12-17T14:40:05.604821",
      "pick_id": "TOT_CON_SEA_20251217",
      "placed_at": "2025-12-17T14:40:05.604821",
      "profit_loss": 0.0,
      "stake": null
    },
    {
      "id": "TOT_IND_CHI_20251217",
      "type": "Total",
      "selection": "OVER 168.0",
      "status": "Pending",
      "result": null,
      "profit_loss": 0.0,
      "created_at": "2025-12-17T14:45:32.343947",
      "pick_id": "TOT_IND_CHI_20251217",
      "placed_at": "2025-12-17T14:45:32.343947"
    },
    {
      "id": "SPD_LVA_NYL_20251218",
      "type": "Spread",
      "selection": "✅ BET: Las Vegas Aces -2.5",
      "profit_loss": 0.0,
      "status": "Pending",
      "result": null,
      "created_at": "2025-12-18T03:30:21.555958",
      "pick_id": "SPD_LVA_NYL_20251218",
      "placed_at": "2025-12-18T03:30:21.555958"
    },
    {
      "id": "TOT_LVA_NYL_20251218",
      "type": "Total",
      "selection": "OVER 172.5",
      "status": "Pending",
      "result": null,
      "profit_loss": 0.0,
      "created_at": "2025-12-18T03:30:21.555963",
      "pick_id": "TOT_LVA_NYL_20251218",
      "placed_at": "2025-12-18T03:30:21.555963"
    },
    {
      "id": "TOT_CON_SEA_20251218",
      "type": "Total",
      "selection": "OVER 158.5",
      "status": "Pending",
      "result": null,
      "profit_loss": 0.0,
      "created_at": "2025-12-18T03:30:21.555965",
      "pick_id": "TOT_CON_SEA_20251218",
      "placed_at": "2025-12-18T03:30:21.555965"
    },
    {
      "id": "TOT_IND_CHI_20251218",
      "type": "Total",
      "selection": "OVER 168.0",
      "status": "Pending",
      "result": null,
      "profit_loss": 0.0,
      "created_at": "2025-12-18T03:30:21.555966",
      "pick_id": "TOT_IND_CHI_20251218",
      "placed_at": "2025-12-18T03:30:21.555966"
    }
  ],
  "summary": {}
}